crevettes/__init__.py
crevettes/harvester.py
crevettes/main.py
crevettes-0.0.5.dist-info/METADATA
crevettes-0.0.5.dist-info/WHEEL
crevettes-0.0.5.dist-info/entry_points.txt
crevettes-0.0.5.dist-info/top_level.txt
crevettes-0.0.5.dist-info/RECORD
