Metadata-Version: 2.1
Name: crevettes
Version: 0.0.5
Summary: A Python utility to capture a thread and commends for a given Reddit thread.
Author-email: Nick Ruest <ruestn@gmail.com>
Requires-Python: >=3.9.9
Requires-Dist: praw>=7.8.1
Requires-Dist: python-dotenv
